setup.py
simpletest/__init__.py
simpletest/test.py
wsssimpletest.egg-info/PKG-INFO
wsssimpletest.egg-info/SOURCES.txt
wsssimpletest.egg-info/dependency_links.txt
wsssimpletest.egg-info/requires.txt
wsssimpletest.egg-info/top_level.txt