Metadata-Version: 1.0
Name: wsssimpletest
Version: 0.0.1
Summary: just a simple test
Home-page: UNKNOWN
Author: yjx
Author-email: not@all.com
License: MIT License
Keywords: simple,test
Platform: any
